odoo8_addon_runbot_website_display-8.0.1.0.0.99.dev1-py2.7-nspkg.pth
odoo_addons/runbot_website_display/__openerp__.py
odoo_addons/runbot_website_display/__init__.py
odoo_addons/runbot_website_display/README.rst
odoo_addons/runbot_website_display/models/__init__.py
odoo_addons/runbot_website_display/models/runbot_repo.py
odoo_addons/runbot_website_display/views/runbot_repo.xml
odoo_addons/runbot_website_display/controllers/runbot_controller.py
odoo_addons/runbot_website_display/controllers/__init__.py
odoo_addons/runbot_website_display/static/description/icon.png
odoo8_addon_runbot_website_display-8.0.1.0.0.99.dev1.dist-info/top_level.txt
odoo8_addon_runbot_website_display-8.0.1.0.0.99.dev1.dist-info/WHEEL
odoo8_addon_runbot_website_display-8.0.1.0.0.99.dev1.dist-info/RECORD
odoo8_addon_runbot_website_display-8.0.1.0.0.99.dev1.dist-info/metadata.json
odoo8_addon_runbot_website_display-8.0.1.0.0.99.dev1.dist-info/DESCRIPTION.rst
odoo8_addon_runbot_website_display-8.0.1.0.0.99.dev1.dist-info/METADATA
odoo8_addon_runbot_website_display-8.0.1.0.0.99.dev1.dist-info/namespace_packages.txt
